{"service": " Batch ", "id": "Batch", "navigation": [{"group": "概述", "id": "area_overview", "articles": [{"id": "link_overview", "title": " 什么是 Azure Batch？ ", "link": "/zh-cn/services/batch/"}, {"id": "link_big_compute", "title": " Batch 和 HPC 资源 ", "link": "https://azure.microsoft.com/zh-cn/documentation/articles/big-compute-resources/"}]}, {"group": "入门", "id": "area_get_started", "articles": [{"id": "link_technical_overview", "title": " 技术概述 ", "link": "https://azure.microsoft.com/zh-cn/documentation/articles/batch-technical-overview/"}, {"id": "link_batch_net", "title": " .NET Batch 库 ", "link": "https://azure.microsoft.com/zh-cn/documentation/articles/batch-dotnet-get-started/"}, {"id": "link_batchapps_net", "title": " Batch Apps .NET tutorial ", "link": "https://azure.microsoft.com/zh-cn/documentation/articles/batch-apps-dotnet-get-started/"}, {"id": "link_batch_psh", "title": " 批处理 PowerShell cmdlet ", "link": "https://azure.microsoft.com/zh-cn/documentation/articles/batch-powershell-cmdlets-get-started/"}]}, {"group": "开发", "id": "area_develop", "articles": [{"id": "link_batch_api_basics", "title": " API 基础知识 ", "link": "https://azure.microsoft.com/zh-cn/documentation/articles/batch-api-basics/"}, {"id": "link_batch_autoscaling", "title": " Autoscale compute nodes ", "link": "https://azure.microsoft.com/zh-cn/documentation/articles/batch-automatic-scaling/"}, {"id": "link_batch_list_queries", "title": " 高效列表查询 ", "link": "https://azure.microsoft.com/zh-cn/documentation/articles/batch-efficient-list-queries/"}, {"id": "link_batch_lib_tools", "title": " 开发库和工具 ", "link": "https://azure.microsoft.com/zh-cn/documentation/articles/batch-development-libraries-tools/"}]}, {"group": "示例", "id": "area_resources", "articles": [{"id": "link_image_batch", "title": " ImageMagick 与 Batch ", "link": "https://github.com/Azure/azure-batch-samples/tree/master/CSharp/ImgProc"}, {"id": "link_image_batch_apps", "title": " ImageMagick 与 Batch 应用 ", "link": "https://code.msdn.microsoft.com/Azure-Batch-Apps-Samples-dd781172"}, {"id": "link_batch_explorer", "title": " 使用 Batch 资源管理器 ", "link": "http://blogs.technet.com/b/windowshpc/archive/2015/01/20/azure-batch-explorer-sample-walkthrough.aspx"}, {"id": "link_batch_apps_blender", "title": " 将 Blender 与 Batch 应用配合使用 ", "link": "https://github.com/Azure/azure-batch-apps-blender"}, {"id": "link_batch_apps_python_sample", "title": " 将 Python 与 Batch 应用配合使用 ", "link": "https://github.com/Azure/azure-batch-apps-python/tree/master/samples/imagemagick_sample"}, {"id": "link_more_samples", "title": " 更多示例 ", "link": "https://github.com/Azure/azure-batch-samples"}]}, {"group": "参考", "id": "area_reference", "articles": [{"id": "link_batch_rest_api", "title": " Batch REST API 参考 ", "link": "https://msdn.microsoft.com/library/azure/dn820158.aspx"}, {"id": "link_batch_apps_rest_api", "title": " Batch 应用程序 REST API 参考 ", "link": "https://msdn.microsoft.com/library/azure/dn820126.aspx"}, {"id": "link_batch_net_api", "title": " Batch .NET 客户端库引用 ", "link": "https://msdn.microsoft.com/library/azure/dn865466.aspx"}, {"id": "link_batch_apps_python", "title": " Batch 应用 Python 客户端 ", "link": "https://github.com/Azure/azure-batch-apps-python"}]}]}